ip_range-0.0.6.dist-info/METADATA
ip_range-0.0.6.dist-info/RECORD
ip_range-0.0.6.dist-info/WHEEL
ip_range-0.0.6.dist-info/top_level.txt
iprange/__init__.py
iprange/iprange.py
